PyEmailHandler/__init__.py
PyEmailHandler/mailer.py
PyEmailHandler/tools.py
PyEmailHandler/version.py
PyEmailHandler-0.1.3a0.dist-info/METADATA
PyEmailHandler-0.1.3a0.dist-info/WHEEL
PyEmailHandler-0.1.3a0.dist-info/top_level.txt
PyEmailHandler-0.1.3a0.dist-info/RECORD
