Metadata-Version: 2.1
Name: PyEmailHandler
Version: 0.1.3a0
Summary: A simplified tool for mailing services
Author-email: BrewedCoffee <support@kinuseka.us>
Project-URL: homepage, https://gitlab.com/brewedcoffee/PyEmailHandler
Keywords: python,sockets,networking,communication
Classifier: Programming Language :: Python :: 3.10
Classifier: Operating System :: OS Independent
Classifier: Operating System :: Microsoft :: Windows
Classifier: Operating System :: POSIX :: Linux
Classifier: Operating System :: MacOS
Classifier: Intended Audience :: Developers
Classifier: Typing :: Typed
Requires-Python: >=3.7
